LICENSE.md
MANIFEST.in
README.md
requirements.txt
setup.py
aplanat/__init__.py
aplanat/annot.py
aplanat/bars.py
aplanat/base.py
aplanat/bio.py
aplanat/graphics.py
aplanat/hist.py
aplanat/layouts.py
aplanat/lines.py
aplanat/points.py
aplanat/report.py
aplanat/spatial.py
aplanat/util.py
aplanat.egg-info/PKG-INFO
aplanat.egg-info/SOURCES.txt
aplanat.egg-info/dependency_links.txt
aplanat.egg-info/entry_points.txt
aplanat.egg-info/not-zip-safe
aplanat.egg-info/requires.txt
aplanat.egg-info/top_level.txt
aplanat/components/__init__.py
aplanat/components/bcfstats.py
aplanat/components/clonevalidation.py
aplanat/components/demo.py
aplanat/components/depthcoverage.py
aplanat/components/fastcat.py
aplanat/components/mapula.py
aplanat/components/nextclade.py
aplanat/components/simple.py
aplanat/data/bootstrap.min.css
aplanat/data/custom-epi2me.css
aplanat/data/custom-ond.css
aplanat/data/custom-ont.css
aplanat/data/fa-regular-400.ttf
aplanat/data/fa-solid-900.ttf
aplanat/data/fontawesome.css
aplanat/data/jquery-3.6.0.slim.min.js
aplanat/data/nextclade.html
aplanat/data/ond_logo.txt
aplanat/data/ont_logo.txt
aplanat/data/report_template.html
aplanat/data/simple-datatables_latest.css
aplanat/data/simple-datatables_latest.js
aplanat/parsers/__init__.py
aplanat/parsers/bcfstats.py