Metadata-Version: 2.1
Name: aplanat
Version: 0.6.11
Summary: Bokeh plotting API.
Home-page: https://github.com/epi2me-labs/aplanat
Author: cwright
Author-email: cwright@nanoporetech.com
License-File: LICENSE.md
